osmomemo/__init__.py
osmomemo/bundle.py
osmomemo/crypto.py
osmomemo/key.py
osmomemo/omemo.py
osmomemo/storage/__init__.py
osmomemo/storage/api.py
osmomemo/storage/models.py
osmomemo-1.1.2.dist-info/METADATA
osmomemo-1.1.2.dist-info/WHEEL
osmomemo-1.1.2.dist-info/top_level.txt
osmomemo-1.1.2.dist-info/RECORD
