Metadata-Version: 2.4
Name: osmomemo
Version: 1.1.2
Summary: Python omemo package
Author: osmiumnet
Requires-Python: >=3.10
Requires-Dist: cryptography>=45.0.6
Requires-Dist: pynacl>=1.5.0
Requires-Dist: sqlalchemy>=2.0.43
Dynamic: author
Dynamic: requires-python
